towers/__init__.py
towers/__version__.py
towers/core/__init__.py
towers/core/disk.py
towers/core/errors.py
towers/core/moves.py
towers/core/rod.py
towers/core/rods.py
towers/core/towers.py
towers/core/utils.py
towers/core/validation.py
towers-0.1.1.dist-info/DESCRIPTION.rst
towers-0.1.1.dist-info/METADATA
towers-0.1.1.dist-info/RECORD
towers-0.1.1.dist-info/WHEEL
towers-0.1.1.dist-info/metadata.json
towers-0.1.1.dist-info/top_level.txt
