Metadata-Version: 2.0
Name: towers
Version: 0.1.1
Summary: Towers of Hanoi for Python
Home-page: http://towers.readthedocs.io/en/latest
Author: Francis Horsman
Author-email: francis.horsman@gmail.com
License: MIT
Keywords: towers
Platform: UNKNOWN
Classifier: Development Status :: 4 - Beta
Classifier: Intended Audience :: Developers
Classifier: Operating System :: OS Independent
Classifier: Programming Language :: Python
Classifier: Programming Language :: Python :: 2.6
Classifier: Programming Language :: Python :: 2.7
Classifier: Programming Language :: Python :: 3.5
Classifier: Programming Language :: Python :: 3.6
Classifier: Programming Language :: Python :: Implementation :: CPython
Classifier: Topic :: Software Development :: Libraries :: Python Modules
Requires: six
Requires: pip
Requires: enum34
Requires-Dist: six
Requires-Dist: pip
Requires-Dist: enum34
